pyslate/__init__.py
pyslate/cache.py
pyslate/config.py
pyslate/locales.py
pyslate/parser.py
pyslate/parsetab.py
pyslate/pyslate.py
pyslate/backends/__init__.py
pyslate/backends/example.py
pyslate/backends/json_backend.py
pyslate/backends/postgres_backend.py
pyslate/backends/redis_backend.py
pyslate-1.1.dist-info/DESCRIPTION.rst
pyslate-1.1.dist-info/METADATA
pyslate-1.1.dist-info/RECORD
pyslate-1.1.dist-info/WHEEL
pyslate-1.1.dist-info/metadata.json
pyslate-1.1.dist-info/top_level.txt
tests/__init__.py
tests/parsetab.py
tests/test_parser.py
tests/test_pyslate.py
