Metadata-Version: 1.1
Name: pyslate
Version: 1.1
Summary: A Python library for maintaining grammatically correct i18n (internationalization) of texts used inthe program: translation of messages, formatting dates and numbers to provide multi-language support.
Home-page: https://github.com/GreeKpl/pyslate
Author: Aleksander Chrabaszcz
Author-email: grkalk@gmail.com
License: MIT
Platform: UNKNOWN
Classifier: Development Status :: 5 - Production/Stable
Classifier: Programming Language :: Python :: 2
Classifier: Programming Language :: Python :: 2.7
Classifier: Programming Language :: Python :: 3
Classifier: Programming Language :: Python :: 3.3
Classifier: Programming Language :: Python :: 3.4
Classifier: Programming Language :: Python :: 3.5
Classifier: License :: OSI Approved :: MIT License
